odoo/addons/ssi_git_server_action/README.rst
odoo/addons/ssi_git_server_action/__init__.py
odoo/addons/ssi_git_server_action/__manifest__.py
odoo/addons/ssi_git_server_action/models/__init__.py
odoo/addons/ssi_git_server_action/models/ir_actions.py
odoo/addons/ssi_git_server_action/static/description/icon.png
odoo/addons/ssi_git_server_action/views/ir_actions_views.xml
odoo14_addon_ssi_git_server_action-14.0.1.0.1.dev3.dist-info/METADATA
odoo14_addon_ssi_git_server_action-14.0.1.0.1.dev3.dist-info/WHEEL
odoo14_addon_ssi_git_server_action-14.0.1.0.1.dev3.dist-info/top_level.txt
odoo14_addon_ssi_git_server_action-14.0.1.0.1.dev3.dist-info/RECORD
