Metadata-Version: 2.1
Name: odoo14-addon-ssi_git_server_action
Version: 14.0.1.0.1.dev3
Summary: Git + Server Action
Home-page: https://simetri-sinergi.id
Author: PT. Simetri Sinergi Indonesia, OpenSynergy Indonesia
License: AGPL-3
Classifier: Programming Language :: Python
Classifier: Framework :: Odoo
Classifier: Framework :: Odoo :: 14.0
Classifier: License :: OSI Approved :: GNU Affero General Public License v3
Requires-Python: >=3.6
Requires-Dist: odoo14-addon-ssi-git
Requires-Dist: odoo<14.1dev,>=14.0a
